pygoko-0.3.3.dist-info/METADATA
pygoko-0.3.3.dist-info/WHEEL
pygoko/__pycache__/__init__.cpython-37.pyc
pygoko/__init__.py
pygoko/pygoko.cpython-37m-x86_64-linux-gnu.so
pygoko-0.3.3.dist-info/RECORD
