Metadata-Version: 2.1
Name: pygoko
Version: 0.3.3
Summary: An python interface for goko
Home-Page: https://github.com/elastic/goko
Author: Sven Cattell <scattell@gmail.com>
Author-Email: Sven Cattell <scattell@gmail.com>
License: Apache-2.0
